MANIFEST.in
README.md
setup.cfg
setup.py
Handystats.egg-info/PKG-INFO
Handystats.egg-info/SOURCES.txt
Handystats.egg-info/dependency_links.txt
Handystats.egg-info/not-zip-safe
Handystats.egg-info/top_level.txt
handystats/__init__.py
handystats.egg-info/SOURCES.txt
src/counter.cpp
src/handystats.cpp
tests/requirements.txt