Metadata-Version: 1.1
Name: handystats
Version: 0.1.1
Summary: Python binding for handystats library
Home-page: https://github.com/noxiouz/python-handystats
Author: Anton Tiurin
Author-email: noxiouz@yandex.ru
License:                    GNU LESSER GENERAL PUBLIC LICENSE
